videotooimage/__init__.py
videotooimage/main.py
videotoooimage-2024.5.14.1.0.0.dist-info/METADATA
videotoooimage-2024.5.14.1.0.0.dist-info/WHEEL
videotoooimage-2024.5.14.1.0.0.dist-info/top_level.txt
videotoooimage-2024.5.14.1.0.0.dist-info/RECORD
