Metadata-Version: 2.2
Name: videotoooimage
Version: 2024.5.14.1.0.0
Summary: Video to Image frames converter
Home-page: https://github.com/raghavavidyapriya/videotoooimage
Author: Raghava
Author-email: raghavavidyapriya@gmail.com
License: MIT
Classifier: Development Status :: 5 - Production/Stable
Classifier: Intended Audience :: Developers
Classifier: Programming Language :: Python :: 3.10
Classifier: Topic :: Software Development :: Libraries :: Python Modules
Requires-Dist: opencv-python
Dynamic: author
Dynamic: author-email
Dynamic: classifier
Dynamic: description
Dynamic: description-content-type
Dynamic: home-page
Dynamic: license
Dynamic: requires-dist
Dynamic: summary
